adafruit_mma8451.py
adafruit_circuitpython_mma8451-1.3.27.dist-info/licenses/LICENSE
adafruit_circuitpython_mma8451-1.3.27.dist-info/METADATA
adafruit_circuitpython_mma8451-1.3.27.dist-info/WHEEL
adafruit_circuitpython_mma8451-1.3.27.dist-info/top_level.txt
adafruit_circuitpython_mma8451-1.3.27.dist-info/RECORD
