Metadata-Version: 2.4
Name: adafruit-circuitpython-mma8451
Version: 1.3.27
Summary: CircuitPython library for MMA8451 3-axis accelerometer..
Author-email: Adafruit Industries <circuitpython@adafruit.com>
License: MIT
Project-URL: Homepage, https://github.com/adafruit/Adafruit_CircuitPython_MMA8451
Keywords: adafruit,mma8451,axis,accelerometer,breakout,hardware,micropython,circuitpython
Classifier: Intended Audience :: Developers
Classifier: Topic :: Software Development :: Libraries
Classifier: Topic :: Software Development :: Embedded Systems
Classifier: Topic :: System :: Hardware
Classifier: License :: OSI Approved :: MIT License
Classifier: Programming Language :: Python :: 3
License-File: LICENSE
Requires-Dist: Adafruit-Blinka
Requires-Dist: adafruit-circuitpython-busdevice>=2.2.5
Provides-Extra: optional
Dynamic: license-file
